lightgbm/VERSION.txt
lightgbm/__init__.py
lightgbm/basic.py
lightgbm/callback.py
lightgbm/compat.py
lightgbm/dask.py
lightgbm/engine.py
lightgbm/lib_lightgbm.so
lightgbm/libpath.py
lightgbm/plotting.py
lightgbm/sklearn.py
lightgbm_no_openmp-3.2.1.25.dist-info/licenses/LICENSE
lightgbm_no_openmp-3.2.1.25.dist-info/METADATA
lightgbm_no_openmp-3.2.1.25.dist-info/WHEEL
lightgbm_no_openmp-3.2.1.25.dist-info/top_level.txt
lightgbm_no_openmp-3.2.1.25.dist-info/RECORD
