Metadata-Version: 2.4
Name: lightgbm-no-openmp
Version: 3.2.1.25
Summary: LightGBM Python Package
Home-page: https://github.com/microsoft/LightGBM
Maintainer: 
Maintainer-email: 
License: The MIT License (Microsoft)
Classifier: Development Status :: 5 - Production/Stable
Classifier: Intended Audience :: Science/Research
Classifier: License :: OSI Approved :: MIT License
Classifier: Natural Language :: English
Classifier: Operating System :: MacOS
Classifier: Operating System :: Microsoft :: Windows
Classifier: Operating System :: POSIX
Classifier: Operating System :: Unix
Classifier: Programming Language :: Python :: 3
Classifier: Programming Language :: Python :: 3.6
Classifier: Programming Language :: Python :: 3.7
Classifier: Programming Language :: Python :: 3.8
Classifier: Programming Language :: Python :: 3.9
Classifier: Topic :: Scientific/Engineering :: Artificial Intelligence
License-File: LICENSE
Requires-Dist: wheel
Requires-Dist: numpy
Requires-Dist: scipy
Requires-Dist: scikit-learn!=0.22.0
Provides-Extra: dask
Requires-Dist: dask[array]>=2.0.0; extra == "dask"
Requires-Dist: dask[dataframe]>=2.0.0; extra == "dask"
Requires-Dist: dask[distributed]>=2.0.0; extra == "dask"
Requires-Dist: pandas; extra == "dask"
Dynamic: classifier
Dynamic: description
Dynamic: home-page
Dynamic: license
Dynamic: license-file
Dynamic: provides-extra
Dynamic: requires-dist
Dynamic: summary
